demo_lib_lol.py
demo_lib_lol-0.0.3.dist-info/LICENSE
demo_lib_lol-0.0.3.dist-info/WHEEL
demo_lib_lol-0.0.3.dist-info/METADATA
demo_lib_lol-0.0.3.dist-info/RECORD
