Metadata-Version: 2.1
Name: demo_lib_lol
Version: 0.0.3
Summary: This is just a demo lib...
Author-email: sohail-unity <sohail.khan@unity3d.com>
Classifier: License :: OSI Approved :: MIT License
Requires-Dist: demo_transitive_dep_lol
